motifdata/_Motif.py
motifdata/__init__.py
motifdata/_convert.py
motifdata/_io.py
motifdata/_transform.py
motifdata/_utils.py
motifdata/resources/filters_out.meme
motifdata/resources/jaspar_out.meme
motifdata/resources/sample.meme
motifdata/resources/sample.motifs
motifdata/resources/sample.pfm
motifdata/resources/sample.sites
motifdata/resources/sample_filter.meme
motifdata/resources/sample_filters.meme
motifdata/resources/sample_out.meme
motifdata/resources/sample_out.motifs
motifdata-0.1.2.dist-info/LICENSE
motifdata-0.1.2.dist-info/METADATA
motifdata-0.1.2.dist-info/WHEEL
motifdata-0.1.2.dist-info/RECORD
